fractional_uplift/__init__.py
fractional_uplift/base_models_test.py
fractional_uplift/constants.py
fractional_uplift/datasets_test.py
fractional_uplift/evaluate.py
fractional_uplift/evaluate_test.py
fractional_uplift/example_data.py
fractional_uplift/example_data_test.py
fractional_uplift/fractional_uplift_test.py
fractional_uplift/meta_learners.py
fractional_uplift/meta_learners_test.py
fractional_uplift/object_duplicator.py
fractional_uplift/object_duplicator_test.py
fractional_uplift/base_models/__init__.py
fractional_uplift/base_models/_base.py
fractional_uplift/base_models/tf_decision_forests.py
fractional_uplift/base_models/tf_decision_forests_test.py
fractional_uplift/datasets/__init__.py
fractional_uplift/datasets/_base.py
fractional_uplift/datasets/pandas.py
fractional_uplift-0.0.1.dist-info/LICENSE
fractional_uplift-0.0.1.dist-info/METADATA
fractional_uplift-0.0.1.dist-info/WHEEL
fractional_uplift-0.0.1.dist-info/top_level.txt
fractional_uplift-0.0.1.dist-info/RECORD
