Metadata-Version: 2.1
Name: fractional-uplift
Version: 0.0.1
Summary: Package for performing uplift modeling that is aware of the cost of treatment.
Home-page: https://github.com/google-marketing-solutions/fractional_uplift
Author: Google gTech Ads Data Science
License: Apache 2.0
Classifier: Development Status :: 3 - Alpha
Classifier: Intended Audience :: Developers
Classifier: Intended Audience :: Science/Research
Classifier: License :: OSI Approved :: Apache Software License
Classifier: Topic :: Scientific/Engineering :: Mathematics
Classifier: Programming Language :: Python :: 3.10
Requires-Python: >=3.10
License-File: LICENSE
Requires-Dist: numpy
Requires-Dist: pandas
Requires-Dist: scikit-learn
Requires-Dist: tensorflow
Requires-Dist: tensorflow-decision-forests
